{
  "tradingDate": "2026-07-17",
  "buckets": {
    "2026-07-17T10": [
      {
        "newsId": "8b594211-e618-48ae-ae7a-c91c987d6adc",
        "scripCode": 532856,
        "shortName": "Time Technoplast Ltd",
        "headline": "Company has received a GeM contract from Hindustan Petroleum Corporation Limited for the supply of 1,40,000 numbers of 10 kg Composite LPG Cylinders, valued at approximately Rs. 38.14 crore.",
        "announcedAt": "2026-07-17T10:59:31.437+05:30",
        "url": "https://www.bseindia.com/stock-share-price/time-technoplast-ltd/timetechno/532856/",
        "rawTime": "2026-07-17T10:59:31.437"
      },
      {
        "newsId": "d1439a28-5ed4-4465-805d-89a6a41b12f9",
        "scripCode": 544047,
        "shortName": "Siyaram Recycling Industries Ltd",
        "headline": "Intimation with regards to \"Siyaram Recycling\" secured order amounting to Rs. 99,23,800 pursuant to Regulation 30 of SEBI (Listing Obligation and Disclosure Requirements) Regulation, 2015",
        "announcedAt": "2026-07-17T10:54:07.143+05:30",
        "url": "https://www.bseindia.com/stock-share-price/siyaram-recycling-industries-ltd/siyaram/544047/",
        "rawTime": "2026-07-17T10:54:07.143"
      },
      {
        "newsId": "63134146-b528-4829-958d-d3932ee75aeb",
        "scripCode": 544334,
        "shortName": "Indobell Insulations Ltd",
        "headline": "New Domestic Order valuing Rs 4,53,51,530.00",
        "announcedAt": "2026-07-17T10:53:32.543+05:30",
        "url": "https://www.bseindia.com/stock-share-price/indobell-insulations-ltd/indobell/544334/",
        "rawTime": "2026-07-17T10:53:32.543"
      },
      {
        "newsId": "8446165a-486b-48ff-9311-7f863a1dd1c6",
        "scripCode": 544334,
        "shortName": "Indobell Insulations Ltd",
        "headline": "New Domestic Order valuing Rs 2,19,40,477.50",
        "announcedAt": "2026-07-17T10:33:14.007+05:30",
        "url": "https://www.bseindia.com/stock-share-price/indobell-insulations-ltd/indobell/544334/",
        "rawTime": "2026-07-17T10:33:14.007"
      },
      {
        "newsId": "6e89ed98-ad00-4092-95d1-09fd6b275461",
        "scripCode": 544291,
        "shortName": "Rajesh Power Services Ltd",
        "headline": "Intimation of Orders received from Paschim Gujarat Vij Company Limited (PGVCL) and Rajasthan Rajya Vidyut Prasaran Nigam Limited (RVPNL).",
        "announcedAt": "2026-07-17T10:20:24.830+05:30",
        "url": "https://www.bseindia.com/stock-share-price/rajesh-power-services-ltd/rajesh/544291/",
        "rawTime": "2026-07-17T10:20:24.83"
      }
    ],
    "2026-07-17T12": [
      {
        "newsId": "6ebfd1bf-f4e2-412b-9ebb-ea0745bcb452",
        "scripCode": 539006,
        "shortName": "PTC Industries Ltd",
        "headline": "As enclosed.",
        "announcedAt": "2026-07-17T12:29:36.943+05:30",
        "url": "https://www.bseindia.com/stock-share-price/ptc-industries-ltd/ptcil/539006/",
        "rawTime": "2026-07-17T12:29:36.943"
      },
      {
        "newsId": "94654cd5-7aea-4f78-9693-d4073b5345d3",
        "scripCode": 544334,
        "shortName": "Indobell Insulations Ltd",
        "headline": "New Domestic Order Valuing Rs 15,660,960.00",
        "announcedAt": "2026-07-17T12:02:02.967+05:30",
        "url": "https://www.bseindia.com/stock-share-price/indobell-insulations-ltd/indobell/544334/",
        "rawTime": "2026-07-17T12:02:02.967"
      }
    ],
    "2026-07-17T11": [
      {
        "newsId": "69ca9e9e-2c7a-4caf-a867-3adde7d0165f",
        "scripCode": 544334,
        "shortName": "Indobell Insulations Ltd",
        "headline": "New Domestic Order Valuing Rs 48,739,015.00",
        "announcedAt": "2026-07-17T11:40:40.043+05:30",
        "url": "https://www.bseindia.com/stock-share-price/indobell-insulations-ltd/indobell/544334/",
        "rawTime": "2026-07-17T11:40:40.043"
      },
      {
        "newsId": "1422ef18-8d65-4263-b752-4b71e8e1bc2a",
        "scripCode": 544334,
        "shortName": "Indobell Insulations Ltd",
        "headline": "New Domestic Order valuing Rs 31,504,000.00",
        "announcedAt": "2026-07-17T11:16:14.080+05:30",
        "url": "https://www.bseindia.com/stock-share-price/indobell-insulations-ltd/indobell/544334/",
        "rawTime": "2026-07-17T11:16:14.08"
      }
    ],
    "2026-07-17T14": [
      {
        "newsId": "ed4fdee1-8d67-419a-a4cf-116539c205f7",
        "scripCode": 544277,
        "shortName": "Waaree Energies Ltd",
        "headline": "Receipt of Order",
        "announcedAt": "2026-07-17T14:33:25.330+05:30",
        "url": "https://www.bseindia.com/stock-share-price/waaree-energies-ltd/waareeener/544277/",
        "rawTime": "2026-07-17T14:33:25.33"
      },
      {
        "newsId": "dbd80116-7dab-4054-9455-03eb394ba1d6",
        "scripCode": 543971,
        "shortName": "Bondada Engineering Ltd",
        "headline": "Intimation of receipt of work order.",
        "announcedAt": "2026-07-17T14:11:38.677+05:30",
        "url": "https://www.bseindia.com/stock-share-price/bondada-engineering-ltd/bondada/543971/",
        "rawTime": "2026-07-17T14:11:38.677"
      }
    ],
    "2026-07-17T13": [
      {
        "newsId": "dc084a1d-69e7-487f-9e5e-85fa043aee9a",
        "scripCode": 544822,
        "shortName": "Laser Power & Infra Ltd",
        "headline": "Intimation of receipt of first Letter of Intent for the supply and installation of High Temperature Low Sag (HTLS) conductors from Himachal Pradesh State Electricity Board Limited.",
        "announcedAt": "2026-07-17T13:28:34.123+05:30",
        "url": "https://www.bseindia.com/stock-share-price/laser-power--infra-ltd/laserpower/544822/",
        "rawTime": "2026-07-17T13:28:34.123"
      }
    ],
    "2026-07-17T16": [
      {
        "newsId": "c689d6f6-1d34-4494-aae4-8714ab729777",
        "scripCode": 543941,
        "shortName": "Ahasolar Technologies Ltd",
        "headline": "Intimation of Receipt of Work Order Received.",
        "announcedAt": "2026-07-17T16:27:11.417+05:30",
        "url": "https://www.bseindia.com/stock-share-price/ahasolar-technologies-ltd/ahasolar/543941/",
        "rawTime": "2026-07-17T16:27:11.417"
      }
    ],
    "2026-07-17T15": [
      {
        "newsId": "1e06c6d9-d5c0-42ff-ad5e-601ddd22ad79",
        "scripCode": 522134,
        "shortName": "Artson Ltd",
        "headline": "Receipt of Letter of Intent for an Award - details enclosed.",
        "announcedAt": "2026-07-17T15:51:42.823+05:30",
        "url": "https://www.bseindia.com/stock-share-price/artson-ltd/artson/522134/",
        "rawTime": "2026-07-17T15:51:42.823"
      }
    ]
  },
  "meta": {
    "lastUpdated": "2026-07-17T16:46:42.613+05:30",
    "checksum": "96de64c0b1978c78e7f4b41d619791f731a03f90a6708d8b6cf1253a3a199522",
    "totalAnnouncements": 14,
    "requestCount": 4,
    "retryCount": 0,
    "rawPayloadPath": "data/raw/2026-07-17/awards-164641.json"
  }
}