{
  "tradingDate": "2026-03-31",
  "buckets": {
    "2026-03-31T10": [
      {
        "newsId": "6b0287f8-fb4d-49ca-9706-6964b45338b1",
        "scripCode": 544334,
        "shortName": "Indobell Insulations Ltd",
        "headline": "NEW EXPORT ORDER WORTH 70,700 USD RECEIVED.",
        "announcedAt": "2026-03-31T10:58:44.393+05:30",
        "url": "https://www.bseindia.com/stock-share-price/indobell-insulations-ltd/indobell/544334/",
        "rawTime": "2026-03-31T10:58:44.393"
      }
    ],
    "2026-03-31T11": [
      {
        "newsId": "36ec980a-188e-4221-9c64-fe030accad32",
        "scripCode": 544334,
        "shortName": "Indobell Insulations Ltd",
        "headline": "NEW EXPORT ORDER WORTH 73,500 USD RECEIVED",
        "announcedAt": "2026-03-31T11:35:04.760+05:30",
        "url": "https://www.bseindia.com/stock-share-price/indobell-insulations-ltd/indobell/544334/",
        "rawTime": "2026-03-31T11:35:04.76"
      },
      {
        "newsId": "b2d7060d-d866-4b4a-ae0b-710034ccc0df",
        "scripCode": 543265,
        "shortName": "RailTel Corporation of India Ltd",
        "headline": "New Order Received",
        "announcedAt": "2026-03-31T11:22:31.733+05:30",
        "url": "https://www.bseindia.com/stock-share-price/railtel-corporation-of-india-ltd/railtel/543265/",
        "rawTime": "2026-03-31T11:22:31.733"
      },
      {
        "newsId": "55b1903a-2dd1-4c4b-b9fc-f1010c091663",
        "scripCode": 533326,
        "shortName": "Texmaco Rail & Engineering Ltd",
        "headline": "Receipt of Order",
        "announcedAt": "2026-03-31T11:17:28.950+05:30",
        "url": "https://www.bseindia.com/stock-share-price/texmaco-rail--engineering-ltd/texrail/533326/",
        "rawTime": "2026-03-31T11:17:28.95"
      }
    ],
    "2026-03-31T12": [
      {
        "newsId": "0e6321da-ba90-44b0-aae1-3572933ee4ab",
        "scripCode": 544243,
        "shortName": "Baazar Style Retail Ltd",
        "headline": "Pursuant to Regulation 30 read with Clause 20 of Para A of Part A of Schedule III of the Securities and Exchange Board of India (Listing Obligations and Disclosure Requirements) Regulations, ....",
        "announcedAt": "2026-03-31T12:32:59.210+05:30",
        "url": "https://www.bseindia.com/stock-share-price/baazar-style-retail-ltd/stylebaaza/544243/",
        "rawTime": "2026-03-31T12:32:59.21"
      }
    ],
    "2026-03-31T15": [
      {
        "newsId": "6dadf344-655e-4db7-938a-51bd34f41dfe",
        "scripCode": 544441,
        "shortName": "Meta Infotech Ltd",
        "headline": "We wish to inform that company has received fresh and renewal order amounting to Rs. 0.70 crores bagged by the Company in the ordinary course of business.",
        "announcedAt": "2026-03-31T15:29:08.440+05:30",
        "url": "https://www.bseindia.com/stock-share-price/meta-infotech-ltd/metainfo/544441/",
        "rawTime": "2026-03-31T15:29:08.44"
      },
      {
        "newsId": "c4916fcd-fe84-46c7-beea-11582cf25d5e",
        "scripCode": 544441,
        "shortName": "Meta Infotech Ltd",
        "headline": "We wish to inform that company has received renewal purchase orders amounting to Rs. 3.06 crores bagged by the Company in the ordinary course of business.",
        "announcedAt": "2026-03-31T15:25:03.840+05:30",
        "url": "https://www.bseindia.com/stock-share-price/meta-infotech-ltd/metainfo/544441/",
        "rawTime": "2026-03-31T15:25:03.84"
      }
    ]
  },
  "meta": {
    "lastUpdated": "2026-03-31T15:50:30.171+05:30",
    "checksum": "88aad48d43c03f3d6674eb25c3293028eb889ae58e4c3351b81a11b28c2d6b3f",
    "totalAnnouncements": 7,
    "requestCount": 8,
    "retryCount": 0,
    "rawPayloadPath": "data/raw/2026-03-31/awards-155029.json"
  }
}